{
  "leanhttp": {
    "content": "Olá Mundo"
  },
  "journals": [
    {
      "id": "46aa6d20-25d5-11ee-a1df-0d1ca801ac92",
      "content": "",
      "created_at": "2023-07-18 22:40:43.891110",
      "updated_at": "2023-07-18 22:40:43.891110"
    },
    {
      "id": "7ba14660-25d6-11ee-8d22-1fb0f71d21ce",
      "content": "",
      "created_at": "2023-07-18 22:49:22.247316",
      "updated_at": "2023-07-18 22:49:22.247317"
    },
    {
      "id": "80e27d60-25d6-11ee-8d22-1fb0f71d21ce",
      "content": "Sábado é dia de descansar um pouco!",
      "created_at": "2023-07-08 22:49:22.468546",
      "updated_at": "2023-07-08 22:49:22.468546"
    },
    {
      "id": "be8f8590-25d6-11ee-b793-c13cc48e3409",
      "content": "",
      "created_at": "2023-07-18 22:51:14.538073",
      "updated_at": "2023-07-18 22:51:14.538074"
    },
    {
      "id": "c9fa57c0-25d6-11ee-b793-c13cc48e3409",
      "content": "teste navegação",
      "created_at": "2023-07-09 22:51:14.754110",
      "updated_at": "2023-07-09 22:51:14.754110"
    },
    {
      "id": "86e97ff0-25d7-11ee-89ed-0f001903cfca",
      "content": "",
      "created_at": "2023-07-18 22:56:50.672659",
      "updated_at": "2023-07-18 22:56:50.672659"
    },
    {
      "id": "88109ad0-25d7-11ee-89ed-0f001903cfca",
      "content": "teste snackbar",
      "created_at": "2023-07-10 22:56:50.893727",
      "updated_at": "2023-07-10 22:56:50.893727"
    }
  ]
}